{"id":"dwxnkggefceh0nl2qn5slq3","title":"Quite OK Image Format","desc":"","updated":1659990042803,"created":1658868762247,"custom":{},"fname":"personal_projects.QOI_ImageFormat","type":"note","vault":{"fsPath":"vault"},"contentHash":"1512724b54717ce564cc1a8257e206a7","links":[{"type":"wiki","from":{"fname":"personal_projects.QOI_ImageFormat","id":"dwxnkggefceh0nl2qn5slq3","vaultName":"vault"},"value":"tags.lang.C_sharp","alias":"tags.lang.C_sharp","position":{"start":{"line":4,"column":1,"offset":20},"end":{"line":4,"column":22,"offset":41},"indent":[]},"xvault":false,"sameFile":false,"to":{"fname":"tags.lang.C_sharp"}},{"type":"wiki","from":{"fname":"personal_projects.QOI_ImageFormat","id":"dwxnkggefceh0nl2qn5slq3","vaultName":"vault"},"value":"tags.engine.unity","alias":"tags.engine.unity","position":{"start":{"line":4,"column":22,"offset":41},"end":{"line":4,"column":43,"offset":62},"indent":[]},"xvault":false,"sameFile":false,"to":{"fname":"tags.engine.unity"}},{"from":{"fname":"root","vaultName":"vault"},"type":"backlink","position":{"start":{"line":21,"column":3,"offset":1090},"end":{"line":21,"column":40,"offset":1127},"indent":[]},"value":"personal_projects.QOI_ImageFormat","alias":"personal_projects.QOI_ImageFormat"}],"anchors":{"core-skills":{"type":"header","text":"Core Skills:","value":"core-skills","line":9,"column":0,"depth":4},"abstract":{"type":"header","text":"Abstract","value":"abstract","line":12,"column":0,"depth":2},"goal":{"type":"header","text":"Goal","value":"goal","line":15,"column":0,"depth":2},"approach":{"type":"header","text":"Approach","value":"approach","line":18,"column":0,"depth":2},"results":{"type":"header","text":"Results","value":"results","line":31,"column":0,"depth":2},"next-steps":{"type":"header","text":"Next Steps","value":"next-steps","line":33,"column":0,"depth":2}},"children":[],"parent":"ye8wey5twan53et97kb8uv2","data":{}}
